fathon-1.3.3.post1.dist-info/RECORD
fathon-1.3.3.post1.dist-info/LICENSE
fathon-1.3.3.post1.dist-info/WHEEL
fathon-1.3.3.post1.dist-info/top_level.txt
fathon-1.3.3.post1.dist-info/METADATA
fathon/cLoops.h
fathon/ht.cpython-38-darwin.so
fathon/mfdcca.cpython-38-darwin.so
fathon/mfdfa.cpython-38-darwin.so
fathon/__init__.py
fathon/dfa.cpython-38-darwin.so
fathon/dcca.cpython-38-darwin.so
fathon/fathonUtils.py
fathon/.dylibs/libgsl.27.dylib
fathon/.dylibs/libgslcblas.0.dylib
fathon/.dylibs/libgomp.1.dylib
