Metadata-Version: 2.1
Name: fathon
Version: 1.3.3.post1
Summary: A python package for detrended fluctuation analysis (DFA) and related algorithms.
Home-page: https://github.com/stfbnc/fathon.git
Author: Stefano Bianchi
Author-email: fathon.package@gmail.com
License: GPLv3.0
Project-URL: Documentation, https://fathon.readthedocs.io/
Project-URL: Bug Reports, https://github.com/stfbnc/fathon/issues
Project-URL: Source, https://github.com/stfbnc/fathon/
Classifier: License :: OSI Approved :: GNU General Public License v3 (GPLv3)
Classifier: Operating System :: MacOS
Classifier: Operating System :: Unix
Classifier: Operating System :: Microsoft :: Windows
Classifier: Programming Language :: Cython
Classifier: Programming Language :: C
Classifier: Programming Language :: Python :: 3.8
Classifier: Programming Language :: Python :: 3.9
Classifier: Programming Language :: Python :: 3.10
Classifier: Programming Language :: Python :: 3.11
Classifier: Programming Language :: Python :: 3.12
Classifier: Topic :: Scientific/Engineering
Requires-Python: >=3.8
License-File: LICENSE
Requires-Dist: numpy >=1.24.4
